pysqlformat/__init__.py
pysqlformat/__main__.py
pysqlformat/main.py
pysqlformat-0.0.0.1.dist-info/LICENSE
pysqlformat-0.0.0.1.dist-info/METADATA
pysqlformat-0.0.0.1.dist-info/WHEEL
pysqlformat-0.0.0.1.dist-info/entry_points.txt
pysqlformat-0.0.0.1.dist-info/top_level.txt
pysqlformat-0.0.0.1.dist-info/RECORD
